epysode/__init__.py
epysode/accessor.py
epysode/facc.py
epysode/iter.py
epysode/mk.py
epysode/name.py
epysode/to.py
epysode-0.0.3.dist-info/LICENSE
epysode-0.0.3.dist-info/METADATA
epysode-0.0.3.dist-info/WHEEL
epysode-0.0.3.dist-info/top_level.txt
epysode-0.0.3.dist-info/RECORD
