Metadata-Version: 2.1
Name: epysode
Version: 0.0.3
Summary: Utils to work with files.
Home-page: https://github.com/thorwhalen/newut/tree/master/epysode
Author: Thor Whalen
License: mit
Platform: any
License-File: LICENSE
